Workbook

Sheet Ввод
A1: ВВОД ДАННЫХ — редактируй только жёлтые ячейки
A2: Жёлтые ячейки = твои допущения. Зелёные на других листах = расчёт по формулам.
A3: TELEGRAM
A4: Подписчиков в Telegram | B4: 800 | D4: Пороги рангов партнёрки: D=350, C=500, B=1000, A=2500, S=5000
A5: Средний охват одного поста | B5: 700 | D5: Для рангов: D=500, C=750, B=1000, A=1500, S=3000
A6: CPM ниши (₽ за 1000 просмотров поста) | B6: 150 | D6: Игровая ниша в TG: ориентир 100–300 ₽
A7: Продажных интеграций в месяц | B7: 2 | D7: 0 на старте; реально с 500–1000 подписчиков
A8: ВИДЕОПЛОЩАДКИ
A9: Rutube: просмотров в месяц | B9: 6000 | D9: Порог монетизации: самозанятый + 2 видео + 5000 просмотров
A10: Rutube: ставка ₽ / 1000 просмотров | B10: 60 | D10: Ориентир 50–90 ₽
A11: VK Видео: просмотров в месяц | B11: 0 | D11: Порог: 5000 подписчиков сообщества, охваты ≥30%
A12: VK Видео: ставка ₽ / 1000 просмотров | B12: 40 | D12: Ориентир 30–50 ₽ (50–80% rev share)
A13: YouTube: просмотров в месяц | B13: 25000 | D13: Монетизация AdSense в РФ отключена → доход 0 ₽. Нужно для партнёрки
A14: ДЗЕН
A15: Дзен: просмотров статей в месяц | B15: 40000 | D15: Порог монетизации: 30 часов просмотра от подписчиков за 30 дней
A16: Доля дочитываний | B16: 0.3 | D16: Обычно 20–40%
A17: Средняя длительность дочитывания, мин | B17: 2.5 | D17: Для гайдов 2–4 минуты
A18: Ставка ₽ за минуту дочитывания | B18: 0.05 | D18: Ориентир 0,05 ₽
A19: ПОДПИСКИ И ДОНАТЫ
A20: Boosty/клуб: платящих подписчиков | B20: 5 | D20: Реалистично 1–3% от аудитории
A21: Средний чек подписки, ₽/мес | B21: 200 | D21: Тарифы 100 / 250 / 500 ₽
A22: Инфопродукты и консультации: продаж в месяц | B22: 2 | D22: PDF-гайды, разборы
A23: Средний чек продукта, ₽ | B23: 350 | D23: 190–1500 ₽ в зависимости от продукта
A24: ПАРТНЁРКА ФОГЕЙМА (не кэш)
A25: Охват всего контента за месяц (просмотры) | B25: 60000 | D25: TG + YouTube + VK + Rutube + Дзен
A26: CTR на реферальную ссылку | B26: 0.005 | D26: Реально 0,3–1% от всех просмотров; в постах про бонусы и промокоды до 3–5%
A27: Конверсия перехода в регистрацию | B27: 0.35 | D27: Ориентир 30–50%
A28: Доля новых/вернувшихся среди регистраций | B28: 0.25 | D28: Важно: твинки и действующие игроки не засчитываются
A29: Доля дошедших до нужного уровня | B29: 0.5 | D29: 91 ур. в Essence/Legacy, 116 в Main
A30: Бонусов Фогейма за 1 реферала | B30: 700 | D30: Фиксировано правилами Программы
A31: Бонусов Фогейма за ранг в месяц | B31: 6000 | D31: Лимит: D=4000, C=10000, B=20000, A=40000, S=70000
A32: НАЛОГИ
A33: Ставка НПД (самозанятый) | B33: 0.06 | D33: 6% с юрлиц, 4% с физлиц

Sheet Расчёт месяца
A1: РАСЧЁТ ДОХОДА ЗА ОДИН МЕСЯЦ
A2: Источник | B2: Сумма | C2: Как считается / условие
A3: КАШ (живые деньги)
A4: Telegram: продажа интеграций | B4: ='Ввод'!$B$5/1000*'Ввод'!$B$6*'Ввод'!$B$7 | C4: охват/1000 × CPM × число размещений
A5: Rutube: монетизация | B5: ='Ввод'!$B$9/1000*'Ввод'!$B$10 | C5: порог: самозанятый + 2 видео + 5000 просмотров
A6: VK Видео: монетизация | B6: ='Ввод'!$B$11/1000*'Ввод'!$B$12 | C6: порог: 5000 подписчиков сообщества, охваты ≥30%
A7: YouTube: монетизация | B7: =0 | C7: AdSense для авторов из РФ отключён → 0 ₽ (используется для охвата и партнёрки)
A8: Дзен: дочитывания | B8: ='Ввод'!$B$15*'Ввод'!$B$16*'Ввод'!$B$17*'Ввод'!$B$18 | C8: просмотры × доля дочитываний × минуты × ставка; порог 30 ч просмотра от подписчиков
A9: Boosty / платный клуб | B9: ='Ввод'!$B$20*'Ввод'!$B$21 | C9: платящие × средний чек
A10: Инфопродукты и консультации | B10: ='Ввод'!$B$22*'Ввод'!$B$23 | C10: продажи × средний чек
A11: ИТОГО ДОХОД (грязными) | B11: =SUM(B4:B10)
A12: Налог НПД | B12: =-B11*'Ввод'!$B$33
A13: ЧИСТЫМИ НА РУКИ | B13: =B11+B12
A15: ПАРТНЁРКА ФОГЕЙМА (не кэш, а игровая ценность)
A16: Переходов по реферальной ссылке | B16: ='Ввод'!$B$25*'Ввод'!$B$26
A17: Регистраций | B17: =B16*'Ввод'!$B$27
A18: Из них новых/вернувшихся (твинки не считаются) | B18: =B17*'Ввод'!$B$28
A19: Зачтённых рефералов (дошли до уровня) | B19: =B18*'Ввод'!$B$29
A20: Бонусов за рефералов (700 за каждого) | B20: =B19*'Ввод'!$B$30
A21: Бонусов за ранг в месяц (лимит по рангу) | B21: ='Ввод'!$B$31
A22: ИТОГО бонусов Фогейма за месяц (1 бонус = 1 ₽ в магазине) | B22: =B20+B21
C23: Вывести деньгами нельзя: только оплата Прав, премиума, предметов в магазине Фогейма
A25: Суммарный эффект месяца (кэш + игровая ценность) | B25: =B13+B21+B20

Sheet Прогноз 12 мес
A1: ПРОГНОЗ НА 12 МЕСЯЦЕВ — меняй темп роста, остальное пересчитается
A2: Модель: каждый месяц аудитория и просмотры растут на заданный %. Доход рассчитывается по тем же формулам, что и на листе «Расчёт месяца».
A4: Месяц | B4: TG подписчики | C4: Охват поста TG | D4: Интеграций | E4: Просмотры Rutube | F4: Просмотры VK Видео | G4: Просмотры Дзен | H4: Рефералов | I4: Кэш чистыми | J4: Бонусы Фогейма
A5: Темп роста/мес | B5: 0.35 | C5: 0.3 | D5: 0.3 | E5: 0.45 | F5: 0.4 | G5: 0.4 | H5: 0.3 | I5: ← редактируй
A6: Мес 1 | B6: ='Ввод'!$B$4 | C6: ='Ввод'!$B$5 | D6: ='Ввод'!$B$7 | E6: ='Ввод'!$B$9 | F6: ='Ввод'!$B$11 | G6: ='Ввод'!$B$15 | H6: =('Ввод'!$B$25*'Ввод'!$B$26*'Ввод'!$B$27*'Ввод'!$B$28*'Ввод'!$B$29) | I6: =(C6/1000*'Ввод'!$B$6*D6+E6/1000*'Ввод'!$B$10+F6/1000*'Ввод'!$B$12+G6*'Ввод'!$B$16*'Ввод'!$B$17*'Ввод'!$B$18+'Ввод'!$B$20*'Ввод'!$B$21+'Ввод'!$B$22*'Ввод'!$B$23)*(1-'Ввод'!$B$33) | J6: =H6*'Ввод'!$B$30+'Ввод'!$B$31
A7: Мес 2 | B7: =B6*(1+B$5) | C7: =C6*(1+C$5) | D7: =D6*(1+D$5) | E7: =E6*(1+E$5) | F7: =F6*(1+F$5) | G7: =G6*(1+G$5) | H7: =H6*(1+$H$5) | I7: =(C7/1000*'Ввод'!$B$6*D7+E7/1000*'Ввод'!$B$10+F7/1000*'Ввод'!$B$12+G7*'Ввод'!$B$16*'Ввод'!$B$17*'Ввод'!$B$18+'Ввод'!$B$20*'Ввод'!$B$21+'Ввод'!$B$22*'Ввод'!$B$23)*(1-'Ввод'!$B$33) | J7: =H7*'Ввод'!$B$30+'Ввод'!$B$31
A8: Мес 3 | B8: =B7*(1+B$5) | C8: =C7*(1+C$5) | D8: =D7*(1+D$5) | E8: =E7*(1+E$5) | F8: =F7*(1+F$5) | G8: =G7*(1+G$5) | H8: =H7*(1+$H$5) | I8: =(C8/1000*'Ввод'!$B$6*D8+E8/1000*'Ввод'!$B$10+F8/1000*'Ввод'!$B$12+G8*'Ввод'!$B$16*'Ввод'!$B$17*'Ввод'!$B$18+'Ввод'!$B$20*'Ввод'!$B$21+'Ввод'!$B$22*'Ввод'!$B$23)*(1-'Ввод'!$B$33) | J8: =H8*'Ввод'!$B$30+'Ввод'!$B$31
A9: Мес 4 | B9: =B8*(1+B$5) | C9: =C8*(1+C$5) | D9: =D8*(1+D$5) | E9: =E8*(1+E$5) | F9: =F8*(1+F$5) | G9: =G8*(1+G$5) | H9: =H8*(1+$H$5) | I9: =(C9/1000*'Ввод'!$B$6*D9+E9/1000*'Ввод'!$B$10+F9/1000*'Ввод'!$B$12+G9*'Ввод'!$B$16*'Ввод'!$B$17*'Ввод'!$B$18+'Ввод'!$B$20*'Ввод'!$B$21+'Ввод'!$B$22*'Ввод'!$B$23)*(1-'Ввод'!$B$33) | J9: =H9*'Ввод'!$B$30+'Ввод'!$B$31
A10: Мес 5 | B10: =B9*(1+B$5) | C10: =C9*(1+C$5) | D10: =D9*(1+D$5) | E10: =E9*(1+E$5) | F10: =F9*(1+F$5) | G10: =G9*(1+G$5) | H10: =H9*(1+$H$5) | I10: =(C10/1000*'Ввод'!$B$6*D10+E10/1000*'Ввод'!$B$10+F10/1000*'Ввод'!$B$12+G10*'Ввод'!$B$16*'Ввод'!$B$17*'Ввод'!$B$18+'Ввод'!$B$20*'Ввод'!$B$21+'Ввод'!$B$22*'Ввод'!$B$23)*(1-'Ввод'!$B$33) | J10: =H10*'Ввод'!$B$30+'Ввод'!$B$31
A11: Мес 6 | B11: =B10*(1+B$5) | C11: =C10*(1+C$5) | D11: =D10*(1+D$5) | E11: =E10*(1+E$5) | F11: =F10*(1+F$5) | G11: =G10*(1+G$5) | H11: =H10*(1+$H$5) | I11: =(C11/1000*'Ввод'!$B$6*D11+E11/1000*'Ввод'!$B$10+F11/1000*'Ввод'!$B$12+G11*'Ввод'!$B$16*'Ввод'!$B$17*'Ввод'!$B$18+'Ввод'!$B$20*'Ввод'!$B$21+'Ввод'!$B$22*'Ввод'!$B$23)*(1-'Ввод'!$B$33) | J11: =H11*'Ввод'!$B$30+'Ввод'!$B$31
A12: Мес 7 | B12: =B11*(1+B$5) | C12: =C11*(1+C$5) | D12: =D11*(1+D$5) | E12: =E11*(1+E$5) | F12: =F11*(1+F$5) | G12: =G11*(1+G$5) | H12: =H11*(1+$H$5) | I12: =(C12/1000*'Ввод'!$B$6*D12+E12/1000*'Ввод'!$B$10+F12/1000*'Ввод'!$B$12+G12*'Ввод'!$B$16*'Ввод'!$B$17*'Ввод'!$B$18+'Ввод'!$B$20*'Ввод'!$B$21+'Ввод'!$B$22*'Ввод'!$B$23)*(1-'Ввод'!$B$33) | J12: =H12*'Ввод'!$B$30+'Ввод'!$B$31
A13: Мес 8 | B13: =B12*(1+B$5) | C13: =C12*(1+C$5) | D13: =D12*(1+D$5) | E13: =E12*(1+E$5) | F13: =F12*(1+F$5) | G13: =G12*(1+G$5) | H13: =H12*(1+$H$5) | I13: =(C13/1000*'Ввод'!$B$6*D13+E13/1000*'Ввод'!$B$10+F13/1000*'Ввод'!$B$12+G13*'Ввод'!$B$16*'Ввод'!$B$17*'Ввод'!$B$18+'Ввод'!$B$20*'Ввод'!$B$21+'Ввод'!$B$22*'Ввод'!$B$23)*(1-'Ввод'!$B$33) | J13: =H13*'Ввод'!$B$30+'Ввод'!$B$31
A14: Мес 9 | B14: =B13*(1+B$5) | C14: =C13*(1+C$5) | D14: =D13*(1+D$5) | E14: =E13*(1+E$5) | F14: =F13*(1+F$5) | G14: =G13*(1+G$5) | H14: =H13*(1+$H$5) | I14: =(C14/1000*'Ввод'!$B$6*D14+E14/1000*'Ввод'!$B$10+F14/1000*'Ввод'!$B$12+G14*'Ввод'!$B$16*'Ввод'!$B$17*'Ввод'!$B$18+'Ввод'!$B$20*'Ввод'!$B$21+'Ввод'!$B$22*'Ввод'!$B$23)*(1-'Ввод'!$B$33) | J14: =H14*'Ввод'!$B$30+'Ввод'!$B$31
A15: Мес 10 | B15: =B14*(1+B$5) | C15: =C14*(1+C$5) | D15: =D14*(1+D$5) | E15: =E14*(1+E$5) | F15: =F14*(1+F$5) | G15: =G14*(1+G$5) | H15: =H14*(1+$H$5) | I15: =(C15/1000*'Ввод'!$B$6*D15+E15/1000*'Ввод'!$B$10+F15/1000*'Ввод'!$B$12+G15*'Ввод'!$B$16*'Ввод'!$B$17*'Ввод'!$B$18+'Ввод'!$B$20*'Ввод'!$B$21+'Ввод'!$B$22*'Ввод'!$B$23)*(1-'Ввод'!$B$33) | J15: =H15*'Ввод'!$B$30+'Ввод'!$B$31
A16: Мес 11 | B16: =B15*(1+B$5) | C16: =C15*(1+C$5) | D16: =D15*(1+D$5) | E16: =E15*(1+E$5) | F16: =F15*(1+F$5) | G16: =G15*(1+G$5) | H16: =H15*(1+$H$5) | I16: =(C16/1000*'Ввод'!$B$6*D16+E16/1000*'Ввод'!$B$10+F16/1000*'Ввод'!$B$12+G16*'Ввод'!$B$16*'Ввод'!$B$17*'Ввод'!$B$18+'Ввод'!$B$20*'Ввод'!$B$21+'Ввод'!$B$22*'Ввод'!$B$23)*(1-'Ввод'!$B$33) | J16: =H16*'Ввод'!$B$30+'Ввод'!$B$31
A17: Мес 12 | B17: =B16*(1+B$5) | C17: =C16*(1+C$5) | D17: =D16*(1+D$5) | E17: =E16*(1+E$5) | F17: =F16*(1+F$5) | G17: =G16*(1+G$5) | H17: =H16*(1+$H$5) | I17: =(C17/1000*'Ввод'!$B$6*D17+E17/1000*'Ввод'!$B$10+F17/1000*'Ввод'!$B$12+G17*'Ввод'!$B$16*'Ввод'!$B$17*'Ввод'!$B$18+'Ввод'!$B$20*'Ввод'!$B$21+'Ввод'!$B$22*'Ввод'!$B$23)*(1-'Ввод'!$B$33) | J17: =H17*'Ввод'!$B$30+'Ввод'!$B$31
A18: ИТОГО за 12 мес | I18: =SUM(I6:I17) | J18: =SUM(J6:J17)
A20: Это модель, а не обещание. Ключевой драйвер — регулярность публикаций и скорость реакции на патчи.

Sheet Пороги и ставки
A1: ПОРОГИ ПОДКЛЮЧЕНИЯ МОНЕТИЗАЦИИ И ПАРТНЁРКИ
A2: Площадка / программа | B2: Порог подключения | C2: Формула / ставка | D2: Комментарий
A3: Партнёрка Фогейма (вход, L2) | B3: 18+; от 4000 просмотров ИЛИ 4 публикации на Twitch/YouTube за месяц; >50% материалов про игру; нет фрода и нарушения АП | C3: Бонусы, промокоды, премиум, PTS | D3: Заявка: ru.4game.com/partners/ ; рассматривают в начале месяца; куратор пишет в Telegram
A4: Партнёрка: Telegram-шкала | B4: D: 350 подп. / охват 500. C: 500 / 750. B: 1000 / 1000. A: 2500 / 1500. S: 5000 / 3000 | C4: 700 бонусов за реферала + до 70 000 бонусов/мес | D4: Показатели TG не суммируются с YouTube/Twitch
A5: Партнёрка: учёт контента | B5: Видео ≥3 минут; стрим ≥2 часов вживую; AFK-эфиры не засчитываются | C5: Ранги A и S — за рефералов (14 и 25) | D5: Проверка накруток: Social Blade, TwitchTracker, TGstat
A6: Дзен | B6: 30 часов просмотра от подписчиков за последние 30 дней | C6: ~0,05 ₽ за минуту дочитывания | D6: 100 000 просмотров/мес ≈ 4 000–12 000 ₽
A7: Rutube | B7: Самозанятый/ИП/юрлицо + 2 видео + 5000 просмотров | C7: 50–90 ₽ / 1000 просмотров + донаты | D7: Самый быстрый кэш с видео в РФ
A8: VK Видео | B8: Открытое сообщество ≥3 мес, 5000 подписчиков, охваты ≥30% (или рост +1250/мес) | C8: 50–80% дохода от рекламы; 30–50 ₽ / 1000 просмотров | D8: Монетизируются только сообщества, не личные страницы; Клипы не монетизируются
A9: YouTube | B9: Монетизация AdSense для авторов из РФ отключена | C9: 0 ₽ | D9: Замедление/ограничения доступа; использовать для охвата и входа в партнёрку
A10: Telegram Ads | B10: Публичный канал, 1000+ подписчиков | C10: 50% дохода от показов, выплаты в TON | D10: В РФ есть ограничения на вывод — проверяй актуальные условия
A11: Telegram: продажа постов | B11: Практически с 500–1000 подписчиков | C11: охват/1000 × CPM (100–300 ₽ в игровой нише) | D11: Обязательна маркировка рекламы через ОРД
A12: Boosty / платный канал | B12: 1000+ лояльных подписчиков | C12: 1–3% аудитории × 150–500 ₽/мес | D12: Прикладная польза, иначе отписки
A13: РСЯ / программа Яндекса | B13: Сайт с трафиком (ориентир 500+ визитов/сут) | C13: за показы/клики и интеграции товаров | D13: Подключать на 4–5 месяце, когда есть сайт
... A16: НПД (самозанятость) | B16: Оформляется бесплатно в «Мой налог» | C16: 4% с физлиц / 6% с юрлиц; лимит 2,4 млн ₽/год | D16: Без неё Rutube-монетизация недоступна

Sheet Прайс интеграций
A1: ПРАЙС-ЛИСТ ДЛЯ РЕКЛАМОДАТЕЛЕЙ (считается от твоего охвата)
A2: Охват поста | B2: Пост 1/24 (низ рынка) | C2: Пост 1/24 (верх рынка) | D2: Нативка (+40%) | E2: Комментарий
A3: CPM низ | B3: 100 | C3: CPM верх | D3: 300
A5: Охват поста | B5: Пост 1/24 (низ) | C5: Пост 1/24 (верх) | D5: Нативная интеграция | E5: Пакет 3 поста
A6: 500 | B6: =A6/1000*$B$3 | C6: =A6/1000*$D$3 | D6: =A6/1000*(($B$3+$D$3)/2)*1.4 | E6: =A6/1000*(($B$3+$D$3)/2)*2.6
A7: 1000 | B7: =A7/1000*$B$3 | C7: =A7/1000*$D$3 | D7: =A7/1000*(($B$3+$D$3)/2)*1.4 | E7: =A7/1000*(($B$3+$D$3)/2)*2.6
A8: 2000 | B8: =A8/1000*$B$3 | C8: =A8/1000*$D$3 | D8: =A8/1000*(($B$3+$D$3)/2)*1.4 | E8: =A8/1000*(($B$3+$D$3)/2)*2.6
A9: 3000 | B9: =A9/1000*$B$3 | C9: =A9/1000*$D$3 | D9: =A9/1000*(($B$3+$D$3)/2)*1.4 | E9: =A9/1000*(($B$3+$D$3)/2)*2.6
A10: 5000 | B10: =A10/1000*$B$3 | C10: =A10/1000*$D$3 | D10: =A10/1000*(($B$3+$D$3)/2)*1.4 | E10: =A10/1000*(($B$3+$D$3)/2)*2.6
A11: 10000 | B11: =A11/1000*$B$3 | C11: =A11/1000*$D$3 | D11: =A11/1000*(($B$3+$D$3)/2)*1.4 | E11: =A11/1000*(($B$3+$D$3)/2)*2.6
A12: 20000 | B12: =A12/1000*$B$3 | C12: =A12/1000*$D$3 | D12: =A12/1000*(($B$3+$D$3)/2)*1.4 | E12: =A12/1000*(($B$3+$D$3)/2)*2.6
A14: Мой текущий охват: подставь значение из листа «Ввод» и смотри строку выше. Формат 1/24 = пост удаляется через сутки, 1/48 = через двое (скидка 20–30%).
A17: Обязательная строка маркировки в каждом рекламном посте:
A18: Реклама. {Наименование рекламодателя, ИНН}. erid: {токен ОРД}
